nmea_gps_logging/__init__.py
nmea_gps_logging/gui.py
nmea_gps_logging/logger.py
nmea_gps_logging-0.0.4.dist-info/LICENSE
nmea_gps_logging-0.0.4.dist-info/METADATA
nmea_gps_logging-0.0.4.dist-info/WHEEL
nmea_gps_logging-0.0.4.dist-info/entry_points.txt
nmea_gps_logging-0.0.4.dist-info/top_level.txt
nmea_gps_logging-0.0.4.dist-info/RECORD
