Metadata-Version: 2.1
Name: nmea-gps-logging
Version: 0.0.4
Summary: A python library for reading USB / serial GPS NMEA0183 devices.
Author-email: Fletcher Thompson <fletho@dtu.dk>
Maintainer-email: Fletcher Thompson <fletho@dtu.dk>
License: MIT License
Project-URL: Homepage, https://github.com/FletcherFT/nmea-gps-logging
Project-URL: Bug Tracker, https://github.com/FletcherFT/nmea-gps-logging/issues
Classifier: Programming Language :: Python :: 3
Classifier: License :: OSI Approved :: MIT License
Classifier: Operating System :: OS Independent
Requires-Python: >=3.10
License-File: LICENSE
Requires-Dist: pyserial
